moc/__init__.py
mocp-0.4.11.dist-info/LICENSE.txt
mocp-0.4.11.dist-info/METADATA
mocp-0.4.11.dist-info/WHEEL
mocp-0.4.11.dist-info/top_level.txt
mocp-0.4.11.dist-info/RECORD
