Metadata-Version: 2.1
Name: mocp
Version: 0.4.11
Summary: A Python library to control the MOC (music on console) audio player
Home-page: https://github.com/kenjyco/mocp
Download-URL: https://github.com/kenjyco/mocp/tarball/v0.4.11
Author: Ken
Author-email: kenjyco@gmail.com
License: MIT
Keywords: moc,mocp,cli,command-line,console audio,mp3 player,kenjyco
Platform: UNKNOWN
Classifier: Development Status :: 3 - Alpha
Classifier: Environment :: Console
Classifier: Intended Audience :: Developers
Classifier: License :: OSI Approved :: MIT License
Classifier: Operating System :: MacOS :: MacOS X
Classifier: Operating System :: POSIX :: Linux
Classifier: Programming Language :: Python :: 3.5
Classifier: Programming Language :: Python
Classifier: Topic :: Multimedia :: Sound/Audio :: Players
Classifier: Topic :: Software Development :: Libraries
License-File: LICENSE.txt
Requires-Dist: bg-helper
Requires-Dist: input-helper
Provides-Extra: extras
Requires-Dist: yt-helper[redis-helper] ; extra == 'extras'
